django_yasp-0.5.0.dist-info/DESCRIPTION.rst
django_yasp-0.5.0.dist-info/METADATA
django_yasp-0.5.0.dist-info/RECORD
django_yasp-0.5.0.dist-info/WHEEL
django_yasp-0.5.0.dist-info/metadata.json
django_yasp-0.5.0.dist-info/top_level.txt
yasp/__init__.py
yasp/admin.py
yasp/apps.py
yasp/middleware.py
yasp/models.py
yasp/urls.py
yasp/views.py
yasp/locale/pt_BR/LC_MESSAGES/django.po
yasp/migrations/0001_initial.py
yasp/migrations/0002_auto_20160729_1814.py
yasp/migrations/0003_auto_20160801_1014.py
yasp/migrations/0004_auto_20160801_1053.py
yasp/migrations/0005_auto_20160801_1652.py
yasp/migrations/0006_auto_20160817_1550.py
yasp/migrations/0007_auto_20160817_1605.py
yasp/migrations/0008_auto_20160901_1606.py
yasp/migrations/0009_auto_20160901_1625.py
yasp/migrations/0010_auto_20160902_1129.py
yasp/migrations/0011_auto_20160902_1625.py
yasp/migrations/0012_auto_20160902_1725.py
yasp/migrations/0013_auto_20160902_1800.py
yasp/migrations/0014_auto_20160906_1633.py
yasp/migrations/0015_auto_20160926_1522.py
yasp/migrations/0016_auto_20160926_1642.py
yasp/migrations/0017_auto_20160926_1830.py
yasp/migrations/0018_auto_20161116_1149.py
yasp/migrations/__init__.py
yasp/static/css/staticpages.css
yasp/static/js/staticpages.js
yasp/templates/yasp/base.html
yasp/templates/yasp/default.html
yasp/templatetags/__init__.py
yasp/templatetags/yasp.py
