Metadata-Version: 2.0
Name: django-yasp
Version: 0.5.0
Summary: Yet Another Static Page Django app.
Home-page: https://github.com/fgmacedo/django-yasp
Author: Fernando Macedo
Author-email: fgmacedo@gmail.com
License: MIT
Keywords: django-yasp
Platform: UNKNOWN
Classifier: Development Status :: 3 - Alpha
Classifier: Framework :: Django
Classifier: Framework :: Django :: 1.9
Classifier: Framework :: Django :: 1.10
Classifier: Intended Audience :: Developers
Classifier: License :: OSI Approved :: BSD License
Classifier: Natural Language :: English
Classifier: Programming Language :: Python :: 2
Classifier: Programming Language :: Python :: 2.7
Classifier: Programming Language :: Python :: 3
Classifier: Programming Language :: Python :: 3.4
Classifier: Programming Language :: Python :: 3.5
